wml/core/__init__.py
wml/core/attributes.py
wml/core/cache_folder.py
wml/core/clujdc.py
wml/core/dataframe_processing.py
wml/core/df_snapshot.py
wml/core/imageio.py
wml/core/jpeg.py
wml/core/resource_loader.py
wml/core/s3.py
wml/core/s3_bulk.py
wml/core/tensor_names.py
wml/core/tf_utils.py
wml/core/version.py
wml/core/code_mapping/__init__.py
wml/core/code_mapping/base.py
wml/core/code_mapping/menu2model.py
wml/core/code_mapping/model2menu.py
wml/core/code_mapping/prim.py
wml/core/datatype/__init__.py
wml/core/datatype/code_mapping.py
wml/core/datatype/confusion.py
wml/core/datatype/cpc.py
wml/core/datatype/dag.py
wml/core/datatype/fr_problem.py
wml/core/datatype/geolocation.py
wml/core/datatype/image_pair.py
wml/core/datatype/menu2slice.py
wml/core/datatype/min_heap.py
wml/core/datatype/opmode.py
wml/core/datatype/taxcode.py
wml/core/datatype/taxtree/__init__.py
wml/core/datatype/taxtree/base.py
wml/core/datatype/taxtree/extra.py
wml/core/ops/__init__.py
wml/core/ops/base.py
wml/core/ops/classification.py
wml/core/ops/duc.py
wml/core/ops/mask.py
wml/core/params/__init__.py
wml/core/params/model.py
wml/core/params/munet.py
wml/core/params/wrangling.py
wml/core/vectorisation/__init__.py
wml/core/vectorisation/base.py
wml/core/vectorisation/timestamp.py
wml/core/vectorisation/weather.py
wml.core-4.27.19.data/scripts/dmt_update_packages.py
wml.core-4.27.19.data/scripts/wml_update_packages.py
wml.core-4.27.19.dist-info/METADATA
wml.core-4.27.19.dist-info/WHEEL
wml.core-4.27.19.dist-info/top_level.txt
wml.core-4.27.19.dist-info/RECORD
